nexus_test/__init__.py
nexus_test/main.py
tests/__init__.py
nexus_test.thomas.in-0.1.8.dist-info/LICENSE
nexus_test.thomas.in-0.1.8.dist-info/METADATA
nexus_test.thomas.in-0.1.8.dist-info/WHEEL
nexus_test.thomas.in-0.1.8.dist-info/top_level.txt
nexus_test.thomas.in-0.1.8.dist-info/RECORD
