Metadata-Version: 2.1
Name: nexus_test.thomas.in
Version: 0.1.8
Summary: nexus test
Author: thomas.in
Author-email: thomas.in@osckorea.com
License: Restricted Software License Agreement
Classifier: Programming Language :: Python :: 3
Classifier: License :: OSI Approved :: MIT License
Classifier: Operating System :: OS Independent
Requires-Python: >=3.6
License-File: LICENSE
Requires-Dist: Django ==5.0
Requires-Dist: requests
Requires-Dist: numpy
